<?xml version="1.0" encoding="utf-8"?>
<!-- *
 * This software is distributed in the hope that it will be useful,
 * but is distributed on an "AS IS" BASIS, WITHOUT WARRANTIES OR
 * CONDITIONS OF ANY KIND, without even the implied warranty of
 * MERCHANTABILITY or FITNESS FOR A PARTICULAR PURPOSE.
 *
 * This software may only be used to program products purchased from
 * Analog Devices for incorporation by you into audio products that
 * are intended for resale to audio product end users. This software
 * may not be distributed whole or in any part to third parties.
 *
 * Copyright © 2026 Analog Devices, Inc. All rights reserved.
 */
-->
<!--NetList XML file-->
<NetList>
    <IC name=" IC 1 " type="ADAU1452">
        <Schematic>
            <Algorithm name="PulseS300Alg1" friendlyname="Pulse Generator " cell="LED Heartbeat.Pulse1 " location="{X=66, Y=128} " Growth="0 " GrowthB="0 " FS="48000">
                <Link pin="O_C21_A0_P1_out" dir="out" link="Link0" />
            </Algorithm>
            <Algorithm name="ICInputADAU145X1" friendlyname="ADAU145x Inputs 0-15 " cell="Input1 " location="{X=-137, Y=194.3954} " Growth="16 " GrowthB="0 " FS="48000">
                <Link pin="O_C0_A0_P1_out" dir="out" link="Link79" />
                <Link pin="O_C0_A0_P2_out" dir="out" link="Link78" />
                <Link pin="O_C0_A0_P3_out" dir="out" link="Link75" />
                <Link pin="O_C0_A0_P4_out" dir="out" link="Link73" />
                <Link pin="O_C0_A0_P5_out" dir="out" link="Link72" />
                <Link pin="O_C0_A0_P6_out" dir="out" link="Link69" />
                <Link pin="O_C0_A0_P7_out" dir="out" link="Link68" />
                <Link pin="O_C0_A0_P8_out" dir="out" link="Link65" />
            </Algorithm>
            <Algorithm name="GPOAlg3001" friendlyname="General Purpose Output " cell="LED Heartbeat.GPO1 " location="{X=216, Y=125} " Growth="0 " GrowthB="0">
                <Link pin="I_C70_A0_P1_in" dir="in" link="Link0" />
            </Algorithm>
            <Algorithm name="EQGenFilterDPS300Alg8" friendlyname="Multi-Channel - Double Precision " cell="Channel_8.Param EQ1_8 " location="{X=160, Y=254} " Growth="1 " GrowthB="1">
                <Link pin="I_C520_A0_P1_in" dir="in" link="Link65" />
                <Link pin="O_C520_A0_P2_out" dir="out" link="Link2" />
            </Algorithm>
            <Algorithm name="EQGenFilterDPS300Alg7" friendlyname="Multi-Channel - Double Precision " cell="Channel_7.Param EQ1_7 " location="{X=160, Y=254} " Growth="1 " GrowthB="1">
                <Link pin="I_C464_A0_P1_in" dir="in" link="Link68" />
                <Link pin="O_C464_A0_P2_out" dir="out" link="Link10" />
            </Algorithm>
            <Algorithm name="EQGenFilterDPS300Alg6" friendlyname="Multi-Channel - Double Precision " cell="Channel_6.Param EQ1_6 " location="{X=160, Y=254} " Growth="1 " GrowthB="1">
                <Link pin="I_C408_A0_P1_in" dir="in" link="Link69" />
                <Link pin="O_C408_A0_P2_out" dir="out" link="Link19" />
            </Algorithm>
            <Algorithm name="EQGenFilterDPS300Alg5" friendlyname="Multi-Channel - Double Precision " cell="Channel_5.Param EQ1_5 " location="{X=160, Y=254} " Growth="1 " GrowthB="1">
                <Link pin="I_C352_A0_P1_in" dir="in" link="Link72" />
                <Link pin="O_C352_A0_P2_out" dir="out" link="Link27" />
            </Algorithm>
            <Algorithm name="EQGenFilterDPS300Alg4" friendlyname="Multi-Channel - Double Precision " cell="Channel_4.Param EQ1_4 " location="{X=160, Y=254} " Growth="1 " GrowthB="1">
                <Link pin="I_C296_A0_P1_in" dir="in" link="Link73" />
                <Link pin="O_C296_A0_P2_out" dir="out" link="Link38" />
            </Algorithm>
            <Algorithm name="EQGenFilterDPS300Alg3" friendlyname="Multi-Channel - Double Precision " cell="Channel_3.Param EQ1_3 " location="{X=160, Y=254} " Growth="1 " GrowthB="1">
                <Link pin="I_C240_A0_P1_in" dir="in" link="Link75" />
                <Link pin="O_C240_A0_P2_out" dir="out" link="Link41" />
            </Algorithm>
            <Algorithm name="EQGenFilterDPS300Alg2" friendlyname="Multi-Channel - Double Precision " cell="Channel_2.Param EQ1_2 " location="{X=160, Y=254} " Growth="1 " GrowthB="1">
                <Link pin="I_C29_A0_P1_in" dir="in" link="Link78" />
                <Link pin="O_C29_A0_P2_out" dir="out" link="Link50" />
            </Algorithm>
            <Algorithm name="EQGenFilterDPS300Alg1" friendlyname="Multi-Channel - Double Precision " cell="Channel_1.Param EQ1 " location="{X=-71, Y=165} " Growth="1 " GrowthB="1">
                <Link pin="I_C44_A0_P1_in" dir="in" link="Link79" />
                <Link pin="O_C44_A0_P2_out" dir="out" link="Link57" />
            </Algorithm>
            <Algorithm name="FIRSigma300Alg8" friendlyname="FIR " cell="Channel_8.FIR1_8 " location="{X=221, Y=247} " Growth="1 " GrowthB="0">
                <Link pin="I_C523_A0_P1_in" dir="in" link="Link2" />
                <Link pin="O_C523_A0_P2_out" dir="out" link="Link8" />
            </Algorithm>
            <Algorithm name="FIRSigma300Alg7" friendlyname="FIR " cell="Channel_7.FIR1_7 " location="{X=221, Y=247} " Growth="1 " GrowthB="0">
                <Link pin="I_C467_A0_P1_in" dir="in" link="Link10" />
                <Link pin="O_C467_A0_P2_out" dir="out" link="Link15" />
            </Algorithm>
            <Algorithm name="FIRSigma300Alg6" friendlyname="FIR " cell="Channel_6.FIR1_6 " location="{X=221, Y=247} " Growth="1 " GrowthB="0">
                <Link pin="I_C411_A0_P1_in" dir="in" link="Link19" />
                <Link pin="O_C411_A0_P2_out" dir="out" link="Link23" />
            </Algorithm>
            <Algorithm name="FIRSigma300Alg5" friendlyname="FIR " cell="Channel_5.FIR1_5 " location="{X=221, Y=247} " Growth="1 " GrowthB="0">
                <Link pin="I_C355_A0_P1_in" dir="in" link="Link27" />
                <Link pin="O_C355_A0_P2_out" dir="out" link="Link29" />
            </Algorithm>
            <Algorithm name="FIRSigma300Alg4" friendlyname="FIR " cell="Channel_4.FIR1_4 " location="{X=221, Y=247} " Growth="1 " GrowthB="0">
                <Link pin="I_C299_A0_P1_in" dir="in" link="Link38" />
                <Link pin="O_C299_A0_P2_out" dir="out" link="Link36" />
            </Algorithm>
            <Algorithm name="FIRSigma300Alg3" friendlyname="FIR " cell="Channel_3.FIR1_3 " location="{X=221, Y=247} " Growth="1 " GrowthB="0">
                <Link pin="I_C243_A0_P1_in" dir="in" link="Link41" />
                <Link pin="O_C243_A0_P2_out" dir="out" link="Link42" />
            </Algorithm>
            <Algorithm name="FIRSigma300Alg2" friendlyname="FIR " cell="Channel_2.FIR1_2 " location="{X=221, Y=247} " Growth="1 " GrowthB="0">
                <Link pin="I_C33_A0_P1_in" dir="in" link="Link50" />
                <Link pin="O_C33_A0_P2_out" dir="out" link="Link56" />
            </Algorithm>
            <Algorithm name="FIRSigma300Alg1" friendlyname="FIR " cell="Channel_1.FIR1 " location="{X=-10, Y=158} " Growth="1 " GrowthB="0">
                <Link pin="I_C49_A0_P1_in" dir="in" link="Link57" />
                <Link pin="O_C49_A0_P2_out" dir="out" link="Link58" />
            </Algorithm>
            <Algorithm name="EQS300MultiDPHWSlewP1Alg29" friendlyname="Multi-Channel HW Slew - Double Precision " cell="Channel_8.High-Pass_15 " location="{X=316, Y=240} " Growth="1 " GrowthB="1">
                <Link pin="I_C526_A0_P1_in" dir="in" link="Link8" />
                <Link pin="O_C526_A0_P2_out" dir="out" link="Link6" />
            </Algorithm>
            <Algorithm name="EQS300MultiDPHWSlewP1Alg25" friendlyname="Multi-Channel HW Slew - Double Precision " cell="Channel_7.High-Pass_13 " location="{X=316, Y=240} " Growth="1 " GrowthB="1">
                <Link pin="I_C470_A0_P1_in" dir="in" link="Link15" />
                <Link pin="O_C470_A0_P2_out" dir="out" link="Link11" />
            </Algorithm>
            <Algorithm name="EQS300MultiDPHWSlewP1Alg21" friendlyname="Multi-Channel HW Slew - Double Precision " cell="Channel_6.High-Pass_11 " location="{X=316, Y=240} " Growth="1 " GrowthB="1">
                <Link pin="I_C414_A0_P1_in" dir="in" link="Link23" />
                <Link pin="O_C414_A0_P2_out" dir="out" link="Link20" />
            </Algorithm>
            <Algorithm name="EQS300MultiDPHWSlewP1Alg17" friendlyname="Multi-Channel HW Slew - Double Precision " cell="Channel_5.High-Pass_9 " location="{X=316, Y=240} " Growth="1 " GrowthB="1">
                <Link pin="I_C358_A0_P1_in" dir="in" link="Link29" />
                <Link pin="O_C358_A0_P2_out" dir="out" link="Link31" />
            </Algorithm>
            <Algorithm name="EQS300MultiDPHWSlewP1Alg13" friendlyname="Multi-Channel HW Slew - Double Precision " cell="Channel_4.High-Pass_7 " location="{X=316, Y=240} " Growth="1 " GrowthB="1">
                <Link pin="I_C302_A0_P1_in" dir="in" link="Link36" />
                <Link pin="O_C302_A0_P2_out" dir="out" link="Link39" />
            </Algorithm>
            <Algorithm name="EQS300MultiDPHWSlewP1Alg9" friendlyname="Multi-Channel HW Slew - Double Precision " cell="Channel_3.High-Pass_5 " location="{X=316, Y=240} " Growth="1 " GrowthB="1">
                <Link pin="I_C246_A0_P1_in" dir="in" link="Link42" />
                <Link pin="O_C246_A0_P2_out" dir="out" link="Link43" />
            </Algorithm>
            <Algorithm name="EQS300MultiDPHWSlewP1Alg5" friendlyname="Multi-Channel HW Slew - Double Precision " cell="Channel_2.High-Pass_3 " location="{X=316, Y=240} " Growth="1 " GrowthB="1">
                <Link pin="I_C37_A0_P1_in" dir="in" link="Link56" />
                <Link pin="O_C37_A0_P2_out" dir="out" link="Link54" />
            </Algorithm>
            <Algorithm name="EQS300MultiDPHWSlewP1Alg1" friendlyname="Multi-Channel HW Slew - Double Precision " cell="Channel_1.High-Pass_1 " location="{X=85, Y=151} " Growth="1 " GrowthB="1">
                <Link pin="I_C125_A0_P1_in" dir="in" link="Link58" />
                <Link pin="O_C125_A0_P2_out" dir="out" link="Link59" />
            </Algorithm>
            <Algorithm name="EQS300MultiDPHWSlewP1Alg30" friendlyname="Multi-Channel HW Slew - Double Precision " cell="Channel_8.High-Pass_16 " location="{X=399, Y=239} " Growth="1 " GrowthB="1">
                <Link pin="I_C529_A0_P1_in" dir="in" link="Link6" />
                <Link pin="O_C529_A0_P2_out" dir="out" link="Link1" />
            </Algorithm>
            <Algorithm name="EQS300MultiDPHWSlewP1Alg26" friendlyname="Multi-Channel HW Slew - Double Precision " cell="Channel_7.High-Pass_14 " location="{X=399, Y=239} " Growth="1 " GrowthB="1">
                <Link pin="I_C473_A0_P1_in" dir="in" link="Link11" />
                <Link pin="O_C473_A0_P2_out" dir="out" link="Link13" />
            </Algorithm>
            <Algorithm name="EQS300MultiDPHWSlewP1Alg22" friendlyname="Multi-Channel HW Slew - Double Precision " cell="Channel_6.High-Pass_12 " location="{X=399, Y=239} " Growth="1 " GrowthB="1">
                <Link pin="I_C417_A0_P1_in" dir="in" link="Link20" />
                <Link pin="O_C417_A0_P2_out" dir="out" link="Link17" />
            </Algorithm>
            <Algorithm name="EQS300MultiDPHWSlewP1Alg18" friendlyname="Multi-Channel HW Slew - Double Precision " cell="Channel_5.High-Pass_10 " location="{X=399, Y=239} " Growth="1 " GrowthB="1">
                <Link pin="I_C361_A0_P1_in" dir="in" link="Link31" />
                <Link pin="O_C361_A0_P2_out" dir="out" link="Link28" />
            </Algorithm>
            <Algorithm name="EQS300MultiDPHWSlewP1Alg14" friendlyname="Multi-Channel HW Slew - Double Precision " cell="Channel_4.High-Pass_8 " location="{X=399, Y=239} " Growth="1 " GrowthB="1">
                <Link pin="I_C305_A0_P1_in" dir="in" link="Link39" />
                <Link pin="O_C305_A0_P2_out" dir="out" link="Link34" />
            </Algorithm>
            <Algorithm name="EQS300MultiDPHWSlewP1Alg10" friendlyname="Multi-Channel HW Slew - Double Precision " cell="Channel_3.High-Pass_6 " location="{X=399, Y=239} " Growth="1 " GrowthB="1">
                <Link pin="I_C249_A0_P1_in" dir="in" link="Link43" />
                <Link pin="O_C249_A0_P2_out" dir="out" link="Link47" />
            </Algorithm>
            <Algorithm name="EQS300MultiDPHWSlewP1Alg6" friendlyname="Multi-Channel HW Slew - Double Precision " cell="Channel_2.High-Pass_4 " location="{X=399, Y=239} " Growth="1 " GrowthB="1">
                <Link pin="I_C47_A0_P1_in" dir="in" link="Link54" />
                <Link pin="O_C47_A0_P2_out" dir="out" link="Link51" />
            </Algorithm>
            <Algorithm name="EQS300MultiDPHWSlewP1Alg2" friendlyname="Multi-Channel HW Slew - Double Precision " cell="Channel_1.High-Pass_2 " location="{X=168, Y=150} " Growth="1 " GrowthB="1">
                <Link pin="I_C137_A0_P1_in" dir="in" link="Link59" />
                <Link pin="O_C137_A0_P2_out" dir="out" link="Link60" />
            </Algorithm>
            <Algorithm name="EQS300MultiDPHWSlewP1Alg31" friendlyname="Multi-Channel HW Slew - Double Precision " cell="Channel_8.Low-Pass_15 " location="{X=483, Y=234} " Growth="1 " GrowthB="1">
                <Link pin="I_C532_A0_P1_in" dir="in" link="Link1" />
                <Link pin="O_C532_A0_P2_out" dir="out" link="Link3" />
            </Algorithm>
            <Algorithm name="EQS300MultiDPHWSlewP1Alg27" friendlyname="Multi-Channel HW Slew - Double Precision " cell="Channel_7.Low-Pass_13 " location="{X=483, Y=234} " Growth="1 " GrowthB="1">
                <Link pin="I_C476_A0_P1_in" dir="in" link="Link13" />
                <Link pin="O_C476_A0_P2_out" dir="out" link="Link12" />
            </Algorithm>
            <Algorithm name="EQS300MultiDPHWSlewP1Alg23" friendlyname="Multi-Channel HW Slew - Double Precision " cell="Channel_6.Low-Pass_11 " location="{X=483, Y=234} " Growth="1 " GrowthB="1">
                <Link pin="I_C420_A0_P1_in" dir="in" link="Link17" />
                <Link pin="O_C420_A0_P2_out" dir="out" link="Link24" />
            </Algorithm>
            <Algorithm name="EQS300MultiDPHWSlewP1Alg19" friendlyname="Multi-Channel HW Slew - Double Precision " cell="Channel_5.Low-Pass_9 " location="{X=483, Y=234} " Growth="1 " GrowthB="1">
                <Link pin="I_C364_A0_P1_in" dir="in" link="Link28" />
                <Link pin="O_C364_A0_P2_out" dir="out" link="Link26" />
            </Algorithm>
            <Algorithm name="EQS300MultiDPHWSlewP1Alg15" friendlyname="Multi-Channel HW Slew - Double Precision " cell="Channel_4.Low-Pass_7 " location="{X=483, Y=234} " Growth="1 " GrowthB="1">
                <Link pin="I_C308_A0_P1_in" dir="in" link="Link34" />
                <Link pin="O_C308_A0_P2_out" dir="out" link="Link37" />
            </Algorithm>
            <Algorithm name="EQS300MultiDPHWSlewP1Alg11" friendlyname="Multi-Channel HW Slew - Double Precision " cell="Channel_3.Low-Pass_5 " location="{X=483, Y=234} " Growth="1 " GrowthB="1">
                <Link pin="I_C252_A0_P1_in" dir="in" link="Link47" />
                <Link pin="O_C252_A0_P2_out" dir="out" link="Link46" />
            </Algorithm>
            <Algorithm name="EQS300MultiDPHWSlewP1Alg7" friendlyname="Multi-Channel HW Slew - Double Precision " cell="Channel_2.Low-Pass_3 " location="{X=483, Y=234} " Growth="1 " GrowthB="1">
                <Link pin="I_C54_A0_P1_in" dir="in" link="Link51" />
                <Link pin="O_C54_A0_P2_out" dir="out" link="Link55" />
            </Algorithm>
            <Algorithm name="EQS300MultiDPHWSlewP1Alg3" friendlyname="Multi-Channel HW Slew - Double Precision " cell="Channel_1.Low-Pass_1 " location="{X=252, Y=145} " Growth="1 " GrowthB="1">
                <Link pin="I_C149_A0_P1_in" dir="in" link="Link60" />
                <Link pin="O_C149_A0_P2_out" dir="out" link="Link61" />
            </Algorithm>
            <Algorithm name="EQS300MultiDPHWSlewP1Alg32" friendlyname="Multi-Channel HW Slew - Double Precision " cell="Channel_8.Low-Pass_16 " location="{X=577, Y=233} " Growth="1 " GrowthB="1">
                <Link pin="I_C535_A0_P1_in" dir="in" link="Link3" />
                <Link pin="O_C535_A0_P2_out" dir="out" link="Link7" />
            </Algorithm>
            <Algorithm name="EQS300MultiDPHWSlewP1Alg28" friendlyname="Multi-Channel HW Slew - Double Precision " cell="Channel_7.Low-Pass_14 " location="{X=577, Y=233} " Growth="1 " GrowthB="1">
                <Link pin="I_C479_A0_P1_in" dir="in" link="Link12" />
                <Link pin="O_C479_A0_P2_out" dir="out" link="Link16" />
            </Algorithm>
            <Algorithm name="EQS300MultiDPHWSlewP1Alg24" friendlyname="Multi-Channel HW Slew - Double Precision " cell="Channel_6.Low-Pass_12 " location="{X=577, Y=233} " Growth="1 " GrowthB="1">
                <Link pin="I_C423_A0_P1_in" dir="in" link="Link24" />
                <Link pin="O_C423_A0_P2_out" dir="out" link="Link18" />
            </Algorithm>
            <Algorithm name="EQS300MultiDPHWSlewP1Alg20" friendlyname="Multi-Channel HW Slew - Double Precision " cell="Channel_5.Low-Pass_10 " location="{X=577, Y=233} " Growth="1 " GrowthB="1">
                <Link pin="I_C367_A0_P1_in" dir="in" link="Link26" />
                <Link pin="O_C367_A0_P2_out" dir="out" link="Link30" />
            </Algorithm>
            <Algorithm name="EQS300MultiDPHWSlewP1Alg16" friendlyname="Multi-Channel HW Slew - Double Precision " cell="Channel_4.Low-Pass_8 " location="{X=577, Y=233} " Growth="1 " GrowthB="1">
                <Link pin="I_C311_A0_P1_in" dir="in" link="Link37" />
                <Link pin="O_C311_A0_P2_out" dir="out" link="Link40" />
            </Algorithm>
            <Algorithm name="EQS300MultiDPHWSlewP1Alg12" friendlyname="Multi-Channel HW Slew - Double Precision " cell="Channel_3.Low-Pass_6 " location="{X=577, Y=233} " Growth="1 " GrowthB="1">
                <Link pin="I_C255_A0_P1_in" dir="in" link="Link46" />
                <Link pin="O_C255_A0_P2_out" dir="out" link="Link44" />
            </Algorithm>
            <Algorithm name="EQS300MultiDPHWSlewP1Alg8" friendlyname="Multi-Channel HW Slew - Double Precision " cell="Channel_2.Low-Pass_4 " location="{X=577, Y=233} " Growth="1 " GrowthB="1">
                <Link pin="I_C57_A0_P1_in" dir="in" link="Link55" />
                <Link pin="O_C57_A0_P2_out" dir="out" link="Link49" />
            </Algorithm>
            <Algorithm name="EQS300MultiDPHWSlewP1Alg4" friendlyname="Multi-Channel HW Slew - Double Precision " cell="Channel_1.Low-Pass_2 " location="{X=346, Y=144} " Growth="1 " GrowthB="1">
                <Link pin="I_C161_A0_P1_in" dir="in" link="Link61" />
                <Link pin="O_C161_A0_P2_out" dir="out" link="Link62" />
            </Algorithm>
            <Algorithm name="DelaySigma300PMAlg8" friendlyname="Growable Delay " cell="Channel_8.Delay1_8 " location="{X=666, Y=226} " Growth="1 " GrowthB="0">
                <Link pin="I_C538_A0_P1_in" dir="in" link="Link7" />
                <Link pin="O_C538_A0_P2_out" dir="out" link="Link5" />
            </Algorithm>
            <Algorithm name="DelaySigma300PMAlg7" friendlyname="Growable Delay " cell="Channel_7.Delay1_7 " location="{X=666, Y=226} " Growth="1 " GrowthB="0">
                <Link pin="I_C482_A0_P1_in" dir="in" link="Link16" />
                <Link pin="O_C482_A0_P2_out" dir="out" link="Link14" />
            </Algorithm>
            <Algorithm name="DelaySigma300PMAlg6" friendlyname="Growable Delay " cell="Channel_6.Delay1_6 " location="{X=666, Y=226} " Growth="1 " GrowthB="0">
                <Link pin="I_C426_A0_P1_in" dir="in" link="Link18" />
                <Link pin="O_C426_A0_P2_out" dir="out" link="Link22" />
            </Algorithm>
            <Algorithm name="DelaySigma300PMAlg5" friendlyname="Growable Delay " cell="Channel_5.Delay1_5 " location="{X=666, Y=226} " Growth="1 " GrowthB="0">
                <Link pin="I_C370_A0_P1_in" dir="in" link="Link30" />
                <Link pin="O_C370_A0_P2_out" dir="out" link="Link32" />
            </Algorithm>
            <Algorithm name="DelaySigma300PMAlg4" friendlyname="Growable Delay " cell="Channel_4.Delay1_4 " location="{X=666, Y=226} " Growth="1 " GrowthB="0">
                <Link pin="I_C314_A0_P1_in" dir="in" link="Link40" />
                <Link pin="O_C314_A0_P2_out" dir="out" link="Link33" />
            </Algorithm>
            <Algorithm name="DelaySigma300PMAlg3" friendlyname="Growable Delay " cell="Channel_3.Delay1_3 " location="{X=666, Y=226} " Growth="1 " GrowthB="0">
                <Link pin="I_C258_A0_P1_in" dir="in" link="Link44" />
                <Link pin="O_C258_A0_P2_out" dir="out" link="Link48" />
            </Algorithm>
            <Algorithm name="DelaySigma300PMAlg2" friendlyname="Growable Delay " cell="Channel_2.Delay1_2 " location="{X=666, Y=226} " Growth="1 " GrowthB="0">
                <Link pin="I_C61_A0_P1_in" dir="in" link="Link49" />
                <Link pin="O_C61_A0_P2_out" dir="out" link="Link52" />
            </Algorithm>
            <Algorithm name="DelaySigma300PMAlg1" friendlyname="Growable Delay " cell="Channel_1.Delay1 " location="{X=435, Y=137} " Growth="1 " GrowthB="0">
                <Link pin="I_C166_A0_P1_in" dir="in" link="Link62" />
                <Link pin="O_C166_A0_P2_out" dir="out" link="Link63" />
            </Algorithm>
            <Algorithm name="OneChanPeakNoPostGainS300_FullRange8" friendlyname="1-Channel Peak Compressor " cell="Channel_8.Compressor2_8 " location="{X=772, Y=206} " Growth="0 " GrowthB="0">
                <Link pin="I_C544_A0_P1_in" dir="in" link="Link5" />
                <Link pin="O_C544_A0_P2_out" dir="out" link="Link4" />
            </Algorithm>
            <Algorithm name="OneChanPeakNoPostGainS300_FullRange7" friendlyname="1-Channel Peak Compressor " cell="Channel_7.Compressor2_7 " location="{X=772, Y=206} " Growth="0 " GrowthB="0">
                <Link pin="I_C488_A0_P1_in" dir="in" link="Link14" />
                <Link pin="O_C488_A0_P2_out" dir="out" link="Link9" />
            </Algorithm>
            <Algorithm name="OneChanPeakNoPostGainS300_FullRange6" friendlyname="1-Channel Peak Compressor " cell="Channel_6.Compressor2_6 " location="{X=772, Y=206} " Growth="0 " GrowthB="0">
                <Link pin="I_C432_A0_P1_in" dir="in" link="Link22" />
                <Link pin="O_C432_A0_P2_out" dir="out" link="Link21" />
            </Algorithm>
            <Algorithm name="OneChanPeakNoPostGainS300_FullRange5" friendlyname="1-Channel Peak Compressor " cell="Channel_5.Compressor2_5 " location="{X=772, Y=206} " Growth="0 " GrowthB="0">
                <Link pin="I_C376_A0_P1_in" dir="in" link="Link32" />
                <Link pin="O_C376_A0_P2_out" dir="out" link="Link25" />
            </Algorithm>
            <Algorithm name="OneChanPeakNoPostGainS300_FullRange4" friendlyname="1-Channel Peak Compressor " cell="Channel_4.Compressor2_4 " location="{X=772, Y=206} " Growth="0 " GrowthB="0">
                <Link pin="I_C320_A0_P1_in" dir="in" link="Link33" />
                <Link pin="O_C320_A0_P2_out" dir="out" link="Link35" />
            </Algorithm>
            <Algorithm name="OneChanPeakNoPostGainS300_FullRange3" friendlyname="1-Channel Peak Compressor " cell="Channel_3.Compressor2_3 " location="{X=772, Y=206} " Growth="0 " GrowthB="0">
                <Link pin="I_C264_A0_P1_in" dir="in" link="Link48" />
                <Link pin="O_C264_A0_P2_out" dir="out" link="Link45" />
            </Algorithm>
            <Algorithm name="OneChanPeakNoPostGainS300_FullRange2" friendlyname="1-Channel Peak Compressor " cell="Channel_2.Compressor2_2 " location="{X=772, Y=206} " Growth="0 " GrowthB="0">
                <Link pin="I_C67_A0_P1_in" dir="in" link="Link52" />
                <Link pin="O_C67_A0_P2_out" dir="out" link="Link53" />
            </Algorithm>
            <Algorithm name="OneChanPeakNoPostGainS300_FullRange1" friendlyname="1-Channel Peak Compressor " cell="Channel_1.Compressor2 " location="{X=541, Y=117} " Growth="0 " GrowthB="0">
                <Link pin="I_C176_A0_P1_in" dir="in" link="Link63" />
                <Link pin="O_C176_A0_P2_out" dir="out" link="Link64" />
            </Algorithm>
            <Algorithm name="MonoNoPostGainS300FullRange16" friendlyname="1-Channel RMS Compressor " cell="Channel_8.Compressor1_8 " location="{X=881, Y=194} " Growth="0 " GrowthB="0">
                <Link pin="I_C541_A0_P1_in" dir="in" link="Link4" />
                <Link pin="O_C541_A0_P2_out" dir="out" link="Link66" />
            </Algorithm>
            <Algorithm name="MonoNoPostGainS300FullRange15" friendlyname="1-Channel RMS Compressor " cell="Channel_7.Compressor1_7 " location="{X=881, Y=194} " Growth="0 " GrowthB="0">
                <Link pin="I_C485_A0_P1_in" dir="in" link="Link9" />
                <Link pin="O_C485_A0_P2_out" dir="out" link="Link67" />
            </Algorithm>
            <Algorithm name="MonoNoPostGainS300FullRange14" friendlyname="1-Channel RMS Compressor " cell="Channel_6.Compressor1_6 " location="{X=881, Y=194} " Growth="0 " GrowthB="0">
                <Link pin="I_C429_A0_P1_in" dir="in" link="Link21" />
                <Link pin="O_C429_A0_P2_out" dir="out" link="Link70" />
            </Algorithm>
            <Algorithm name="MonoNoPostGainS300FullRange13" friendlyname="1-Channel RMS Compressor " cell="Channel_5.Compressor1_5 " location="{X=881, Y=194} " Growth="0 " GrowthB="0">
                <Link pin="I_C373_A0_P1_in" dir="in" link="Link25" />
                <Link pin="O_C373_A0_P2_out" dir="out" link="Link71" />
            </Algorithm>
            <Algorithm name="MonoNoPostGainS300FullRange12" friendlyname="1-Channel RMS Compressor " cell="Channel_4.Compressor1_4 " location="{X=881, Y=194} " Growth="0 " GrowthB="0">
                <Link pin="I_C317_A0_P1_in" dir="in" link="Link35" />
                <Link pin="O_C317_A0_P2_out" dir="out" link="Link74" />
            </Algorithm>
            <Algorithm name="MonoNoPostGainS300FullRange11" friendlyname="1-Channel RMS Compressor " cell="Channel_3.Compressor1_3 " location="{X=881, Y=194} " Growth="0 " GrowthB="0">
                <Link pin="I_C261_A0_P1_in" dir="in" link="Link45" />
                <Link pin="O_C261_A0_P2_out" dir="out" link="Link76" />
            </Algorithm>
            <Algorithm name="MonoNoPostGainS300FullRange10" friendlyname="1-Channel RMS Compressor " cell="Channel_2.Compressor1_2 " location="{X=881, Y=194} " Growth="0 " GrowthB="0">
                <Link pin="I_C64_A0_P1_in" dir="in" link="Link53" />
                <Link pin="O_C64_A0_P2_out" dir="out" link="Link77" />
            </Algorithm>
            <Algorithm name="MonoNoPostGainS300FullRange9" friendlyname="1-Channel RMS Compressor " cell="Channel_1.Compressor1 " location="{X=650, Y=105} " Growth="0 " GrowthB="0">
                <Link pin="I_C171_A0_P1_in" dir="in" link="Link64" />
                <Link pin="O_C171_A0_P2_out" dir="out" link="Link80" />
            </Algorithm>
            <Algorithm name="ICOutADAU145X1" friendlyname="Output " cell="Output 0-7.CH_0 " location="{X=212, Y=-109.9697} " Growth="1 " GrowthB="0">
                <Link pin="I_C869_A0_P1_in" dir="in" link="Link80" />
            </Algorithm>
            <Algorithm name="ICOutADAU145X5" friendlyname="Output " cell="Output 0-7.CH_4 " location="{X=383, Y=-109.9697} " Growth="1 " GrowthB="0">
                <Link pin="I_C923_A0_P1_in" dir="in" link="Link71" />
            </Algorithm>
            <Algorithm name="ICOutADAU145X6" friendlyname="Output " cell="Output 0-7.CH_5 " location="{X=383, Y=75.03032} " Growth="1 " GrowthB="0">
                <Link pin="I_C931_A0_P1_in" dir="in" link="Link70" />
            </Algorithm>
            <Algorithm name="ICOutADAU145X2" friendlyname="Output " cell="Output 0-7.CH_1 " location="{X=212, Y=75.0303} " Growth="1 " GrowthB="0">
                <Link pin="I_C881_A0_P1_in" dir="in" link="Link77" />
            </Algorithm>
            <Algorithm name="ICOutADAU145X3" friendlyname="Output " cell="Output 0-7.CH_2 " location="{X=207, Y=255.5303} " Growth="1 " GrowthB="0">
                <Link pin="I_C895_A0_P1_in" dir="in" link="Link76" />
            </Algorithm>
            <Algorithm name="ICOutADAU145X7" friendlyname="Output " cell="Output 0-7.CH_6 " location="{X=383, Y=254.5303} " Growth="1 " GrowthB="0">
                <Link pin="I_C939_A0_P1_in" dir="in" link="Link67" />
            </Algorithm>
            <Algorithm name="ICOutADAU145X8" friendlyname="Output " cell="Output 0-7.CH_7 " location="{X=383, Y=431.0303} " Growth="1 " GrowthB="0">
                <Link pin="I_C947_A0_P1_in" dir="in" link="Link66" />
            </Algorithm>
            <Algorithm name="ICOutADAU145X4" friendlyname="Output " cell="Output 0-7.CH_3 " location="{X=212, Y=431.0303} " Growth="1 " GrowthB="0">
                <Link pin="I_C903_A0_P1_in" dir="in" link="Link74" />
            </Algorithm>
        </Schematic>
    </IC>
</NetList>